celestialtree/__init__.py
celestialtree/client.py
celestialtree/tools/formatters.py
celestialtree-0.1.1.dist-info/licenses/LICENSE
celestialtree-0.1.1.dist-info/METADATA
celestialtree-0.1.1.dist-info/WHEEL
celestialtree-0.1.1.dist-info/top_level.txt
celestialtree-0.1.1.dist-info/RECORD
