Metadata-Version: 2.4
Name: celestialtree
Version: 0.1.1
Summary: Python client for CelestialTree event provenance service
Author-email: Mr-xiaotian <mingxiaomingtian@gmail.com>
License: MIT License
Project-URL: Homepage, https://github.com/Mr-xiaotian/celestialtree-pyclient
Project-URL: Repository, https://github.com/Mr-xiaotian/celestialtree-pyclient
Project-URL: Issues, https://github.com/Mr-xiaotian/celestialtree-pyclient/issues
Keywords: celestialtree,event,provenance,causality,distributed-systems,task-tracking
Classifier: Development Status :: 3 - Alpha
Classifier: Intended Audience :: Developers
Classifier: License :: OSI Approved :: MIT License
Classifier: Programming Language :: Python :: 3
Classifier: Programming Language :: Python :: 3 :: Only
Classifier: Programming Language :: Python :: 3.8
Classifier: Programming Language :: Python :: 3.9
Classifier: Programming Language :: Python :: 3.10
Classifier: Programming Language :: Python :: 3.11
Classifier: Topic :: Software Development :: Libraries
Classifier: Topic :: System :: Distributed Computing
Requires-Python: >=3.8
License-File: LICENSE
Requires-Dist: requests>=2.28
Dynamic: license-file
